cs_logging/VERSION.txt
cs_logging/__init__.py
cs_logging/logger.py
cs_logging-0.0.3.dev0.dist-info/METADATA
cs_logging-0.0.3.dev0.dist-info/WHEEL
cs_logging-0.0.3.dev0.dist-info/top_level.txt
cs_logging-0.0.3.dev0.dist-info/zip-safe
cs_logging-0.0.3.dev0.dist-info/RECORD
