Metadata-Version: 2.1
Name: cs_logging
Version: 0.0.3.dev0
Summary: logging configuration based on ttbuda hpp file
Author-email: Clark Saben <csaben@mail.umw.edu>
Project-URL: code, https://github.com/csaben/cs-logging
Classifier: Development Status :: 4 - Beta
Classifier: Environment :: Console
Classifier: Topic :: System :: Operating System Kernels :: Linux
Classifier: Programming Language :: Python :: 3.10
Requires-Python: >=3.10.0
Provides-Extra: dev
Requires-Dist: pytest ; extra == 'dev'
Requires-Dist: ruff ; extra == 'dev'
Requires-Dist: black ; extra == 'dev'
Requires-Dist: flake8 ; extra == 'dev'
Requires-Dist: mypy ; extra == 'dev'
